Metadata-Version: 2.1
Name: scann2dxf
Version: 0.1.0
Summary: simple python based scann to dxf converter
Home-page: https://github.com/multigcs/scann2dxf/
Author: Oliver Dippel
Author-email: o.dippel@gmx.de
License: LICENSE
Platform: UNKNOWN
License-File: LICENSE
